EasyFlaskRecaptcha.py
EasyFlaskRecaptcha-1.0.2.dist-info/LICENSE
EasyFlaskRecaptcha-1.0.2.dist-info/METADATA
EasyFlaskRecaptcha-1.0.2.dist-info/WHEEL
EasyFlaskRecaptcha-1.0.2.dist-info/top_level.txt
EasyFlaskRecaptcha-1.0.2.dist-info/RECORD
