Metadata-Version: 2.1
Name: EasyFlaskRecaptcha
Version: 1.0.2
Summary: Easy Integration of Google Recaptcha in Flask
Home-page: https://github.com/pushpenderindia/EasyFlaskRecaptcha
Author: Pushpender Singh
Author-email: pushpendersingh@protonmail.com
License: MIT License
Keywords: flaskrecaptcha,flask,recaptcha,google,python
License-File: LICENSE
Requires-Dist: requests
Requires-Dist: MarkupSafe
